reg_bench/__init__.py
reg_bench/__version__.py
reg_bench/maps/__init__.py
reg_bench/maps/maps.py
reg_bench/ode/__init__.py
reg_bench/ode/integrate.py
reg_bench/ode/not_so_simple_ode.py
reg_bench/ode/simple_ode.py
reg_bench/symbolic_regression/__init__.py
reg_bench/symbolic_regression/keijzer.py
reg_bench/symbolic_regression/korns.py
reg_bench/symbolic_regression/koza.py
reg_bench/symbolic_regression/nguyen.py
reg_bench/symbolic_regression/pagie.py
reg_bench/symbolic_regression/util.py
reg_bench/symbolic_regression/vladislavleva.py
reg_bench/utils.py
reg_bench-0.0.3.dist-info/LICENSE
reg_bench-0.0.3.dist-info/WHEEL
reg_bench-0.0.3.dist-info/METADATA
reg_bench-0.0.3.dist-info/RECORD
