Metadata-Version: 2.1
Name: reg-bench
Version: 0.0.3
Summary: 
Home-page: https://github.com/Ohjeah/regression-benchmarks
License: MIT
Author: Markus Quade
Author-email: info@markusqua.de
Requires-Python: >=3.7,<4.0
Classifier: License :: OSI Approved :: MIT License
Classifier: Programming Language :: Python :: 3
Classifier: Programming Language :: Python :: 3.7
Requires-Dist: derivative (>=0.1.2,<0.2.0)
Requires-Dist: numpy (>=1.15,<2.0)
Requires-Dist: pyodesys (>=0.12.4,<0.13.0)
Requires-Dist: scikit-learn[alldeps] (>=0.20.1,<0.21.0)
Requires-Dist: toolz (>=0.9.0,<0.10.0)
Project-URL: Repository, https://github.com/Ohjeah/regression-benchmarks
